beancmb/__init__.py
beancmb/daily_email_impoter.py
beancmb/pdf_importer.py
beancmb/util.py
tests/__init__.py
tests/pdf_test.py
beancount_cmb_importer-0.1.4.dist-info/METADATA
beancount_cmb_importer-0.1.4.dist-info/WHEEL
beancount_cmb_importer-0.1.4.dist-info/top_level.txt
beancount_cmb_importer-0.1.4.dist-info/RECORD
